kinetic_sdk/__init__.py
kinetic_sdk/generated/__init__.py
kinetic_sdk/generated/client/__init__.py
kinetic_sdk/generated/client/api/__init__.py
kinetic_sdk/generated/client/api/account_api.py
kinetic_sdk/generated/client/api/airdrop_api.py
kinetic_sdk/generated/client/api/app_api.py
kinetic_sdk/generated/client/api/transaction_api.py
kinetic_sdk/generated/client/api_client.py
kinetic_sdk/generated/client/apis/__init__.py
kinetic_sdk/generated/client/configuration.py
kinetic_sdk/generated/client/exceptions.py
kinetic_sdk/generated/client/model/__init__.py
kinetic_sdk/generated/client/model/account_info.py
kinetic_sdk/generated/client/model/app_config.py
kinetic_sdk/generated/client/model/app_config_api.py
kinetic_sdk/generated/client/model/app_config_app.py
kinetic_sdk/generated/client/model/app_config_cluster.py
kinetic_sdk/generated/client/model/app_config_environment.py
kinetic_sdk/generated/client/model/app_config_mint.py
kinetic_sdk/generated/client/model/app_health.py
kinetic_sdk/generated/client/model/balance_response.py
kinetic_sdk/generated/client/model/balance_token.py
kinetic_sdk/generated/client/model/close_account_request.py
kinetic_sdk/generated/client/model/cluster_type.py
kinetic_sdk/generated/client/model/commitment.py
kinetic_sdk/generated/client/model/compiled_inner_instruction.py
kinetic_sdk/generated/client/model/compiled_instruction.py
kinetic_sdk/generated/client/model/confirmation_status.py
kinetic_sdk/generated/client/model/confirmed_signature_info.py
kinetic_sdk/generated/client/model/confirmed_transaction_meta.py
kinetic_sdk/generated/client/model/create_account_request.py
kinetic_sdk/generated/client/model/get_transaction_response.py
kinetic_sdk/generated/client/model/history_response.py
kinetic_sdk/generated/client/model/latest_blockhash_response.py
kinetic_sdk/generated/client/model/make_transfer_request.py
kinetic_sdk/generated/client/model/minimum_rent_exemption_balance_response.py
kinetic_sdk-1.0.0rc16.dist-info/WHEEL
kinetic_sdk-1.0.0rc16.dist-info/METADATA
kinetic_sdk-1.0.0rc16.dist-info/RECORD
