Metadata-Version: 2.1
Name: kinetic-sdk
Version: 1.0.0rc16
Summary: 
Home-page: https://github.com/kin-labs/kinetic-python-sdk
License: MIT
Keywords: solana,blockchain,kin,web3
Author: Kin Foundation
Author-email: dev@kin.org
Requires-Python: >=3.8.1,<4.0.0
Classifier: Intended Audience :: Developers
Classifier: License :: OSI Approved :: MIT License
Classifier: Natural Language :: English
Classifier: Programming Language :: Python :: 3
Classifier: Programming Language :: Python :: 3.9
Classifier: Programming Language :: Python :: 3.10
Classifier: Programming Language :: Python :: 3.7
Classifier: Programming Language :: Python :: 3.8
Classifier: Programming Language :: Python :: 3.9
Requires-Dist: bip-utils (>=2.7.0,<3.0.0)
Requires-Dist: pybase64 (>=1.2.2,<2.0.0)
Requires-Dist: pybip39 (>=0.1.0,<0.2.0)
Requires-Dist: python-dateutil (>=2.8.2,<3.0.0)
Requires-Dist: solana (>=0.27.2,<0.28.0)
Requires-Dist: solders (==0.9.3)
Project-URL: Documentation, https://github.com/kin-labs/kinetic-python-sdk
